linkeddeepdict/__init__.py
linkeddeepdict/linkeddeepdict.py
linkeddeepdict/tools/__init__.py
linkeddeepdict/tools/dtk.py
linkeddeepdict/tools/kwargtools.py
linkeddeepdict-1.1.0.dist-info/LICENSE
linkeddeepdict-1.1.0.dist-info/METADATA
linkeddeepdict-1.1.0.dist-info/WHEEL
linkeddeepdict-1.1.0.dist-info/top_level.txt
linkeddeepdict-1.1.0.dist-info/RECORD
