Metadata-Version: 2.1
Name: linkeddeepdict
Version: 1.1.0
Summary: Linked Deep Dictionaries in Python.
Home-page: https://github.com/dewloosh/LinkedDeepDict
Download-URL: https://github.com/dewloosh/LinkedDeepDict/archive/refs/tags/1.1.0.zip
Author: Bence Balogh
Author-email: benceeok@gmail.com
Classifier: Development Status :: 5 - Production/Stable
Classifier: License :: OSI Approved :: MIT License
Classifier: Programming Language :: Python :: 3.7
Classifier: Programming Language :: Python :: 3.8
Classifier: Programming Language :: Python :: 3.9
Classifier: Programming Language :: Python :: 3.10
Classifier: Programming Language :: Python :: 3 :: Only
Classifier: Operating System :: OS Independent
Requires-Python: >=3.7, <3.11
License-File: LICENSE
Requires-Dist: setuptools
Requires-Dist: wheel
Requires-Dist: six
